ssa_wrapper/__init__.py
ssa_wrapper/resources.py
ssa_wrapper/site.py
ssa_wrapper/ssa_twitter.py
ssa_api_wrapper-0.6.1.dist-info/METADATA
ssa_api_wrapper-0.6.1.dist-info/WHEEL
ssa_api_wrapper-0.6.1.dist-info/top_level.txt
ssa_api_wrapper-0.6.1.dist-info/RECORD
