Metadata-Version: 2.1
Name: ssa-api-wrapper
Version: 0.6.1
Summary: Wrapper for SSA API
Home-page: https://github.com/Phoneguytech75/SSA-API-WRAPPER
Author: Phoneguytech75
License: UNKNOWN
Project-URL: Bug Tracker, https://github.com/pypa/sampleproject/issues
Platform: UNKNOWN
Classifier: Programming Language :: Python :: 3
Classifier: License :: OSI Approved :: MIT License
Classifier: Operating System :: OS Independent
Requires-Python: >=3.6
Requires-Dist: requests
